{
  "version": 1,
  "pages": {
    "index.js": {
      "maxDuration": 10
    },
    "time.js": {
      "maxDuration": 10
    },
    "main.go": {
      "runtime": "go1.x",
      "handler": "main.go"
    },
    "api/time.go": {
      "runtime": "go1.x",
      "handler": "time.bin"
    },
    "edge/_middleware.js": {
      "runtime": "web",
      "env": [],
      "files": ["server/pages/edge/_middleware.js"],
      "name": "pages/edge/_middleware",
      "page": "/edge/time",
      "regexp": "^/edge/time$",
      "sortingIndex": 1
    }
  }
}